fastapi_batteries_included/__init__.py
fastapi_batteries_included/autoapp.py
fastapi_batteries_included/config.py
fastapi_batteries_included/helpers/__init__.py
fastapi_batteries_included/helpers/apispec.py
fastapi_batteries_included/helpers/error_handler.py
fastapi_batteries_included/helpers/metrics.py
fastapi_batteries_included/helpers/routes.py
fastapi_batteries_included/helpers/security/__init__.py
fastapi_batteries_included/helpers/security/api_key.py
fastapi_batteries_included/helpers/security/endpoint_security.py
fastapi_batteries_included/helpers/security/jwk.py
fastapi_batteries_included/helpers/security/jwt.py
fastapi_batteries_included/helpers/security/jwt_parsers.py
fastapi_batteries_included/helpers/security/jwt_user.py
fastapi_batteries_included/helpers/security/protection.py
fastapi_batteries_included/py.typed
fastapi_batteries_included/router_monitoring/__init__.py
fastapi_batteries_included/sqldb.py
fastapi_batteries_included-1.2.4.dist-info/entry_points.txt
fastapi_batteries_included-1.2.4.dist-info/LICENSE.md
fastapi_batteries_included-1.2.4.dist-info/WHEEL
fastapi_batteries_included-1.2.4.dist-info/METADATA
fastapi_batteries_included-1.2.4.dist-info/RECORD
